{
    "Sources": [
        {
            "source": "Sextans(1)",
            "ra_deg": 153.26249999999996,
            "dec_deg": -1.6147222222222224,
            "epoch_year": null,
            "equinox": "ICRS",
            "reference": "McConnachie12",
            "other_references": null,
            "comments": null
        }
    ],
    "ModeledParameters": [
        {
            "model": null,
            "parameter": "MHI",
            "value": 0.0,
            "error": null,
            "error_upper": null,
            "error_lower": null,
            "unit": null,
            "comments": null,
            "reference": "McConnachie12"
        },
        {
            "model": null,
            "parameter": "distance modulus",
            "value": 19.670000076293945,
            "error": null,
            "error_upper": 0.10000000149011612,
            "error_lower": 0.10000000149011612,
            "unit": null,
            "comments": null,
            "reference": "McConnachie12"
        },
        {
            "model": null,
            "parameter": "metallicity",
            "value": -1.9299999475479126,
            "error": null,
            "error_upper": 0.009999999776482582,
            "error_lower": 0.009999999776482582,
            "unit": null,
            "comments": null,
            "reference": "McConnachie12"
        },
        {
            "model": null,
            "parameter": "muVo",
            "value": 27.100000381469727,
            "error": null,
            "error_upper": 0.5,
            "error_lower": 0.5,
            "unit": null,
            "comments": null,
            "reference": "McConnachie12"
        },
        {
            "model": null,
            "parameter": "sigma_g",
            "value": 0.0,
            "error": null,
            "error_upper": 0.0,
            "error_lower": 0.0,
            "unit": null,
            "comments": null,
            "reference": "McConnachie12"
        },
        {
            "model": null,
            "parameter": "sigma_s",
            "value": 7.900000095367432,
            "error": null,
            "error_upper": 1.2999999523162842,
            "error_lower": 1.2999999523162842,
            "unit": null,
            "comments": null,
            "reference": "McConnachie12"
        },
        {
            "model": null,
            "parameter": "vrot_g",
            "value": 0.0,
            "error": null,
            "error_upper": 0.0,
            "error_lower": 0.0,
            "unit": null,
            "comments": null,
            "reference": "McConnachie12"
        },
        {
            "model": null,
            "parameter": "vrot_s",
            "value": 0.0,
            "error": null,
            "error_upper": 0.0,
            "error_lower": 0.0,
            "unit": null,
            "comments": null,
            "reference": "McConnachie12"
        }
    ],
    "Morphology": [
        {
            "position_angle_deg": 56.0,
            "position_angle_error": null,
            "position_angle_error_upper": 5.0,
            "position_angle_error_lower": 5.0,
            "ellipticity": 0.3499999940395355,
            "ellipticity_error": null,
            "ellipticity_error_upper": 0.05000000074505806,
            "ellipticity_error_lower": 0.05000000074505806,
            "half_light_radius_arcmin": 27.799999237060547,
            "half_light_radius_error": null,
            "half_light_radius_error_upper": 1.2000000476837158,
            "half_light_radius_error_lower": 1.2000000476837158,
            "adopted": true,
            "comments": null,
            "reference": "McConnachie12"
        }
    ],
    "Photometry": [
        {
            "band": "Generic/Johnson.V",
            "magnitude": 10.399999618530273,
            "magnitude_error": null,
            "magnitude_error_upper": 0.5,
            "magnitude_error_lower": 0.5,
            "telescope": null,
            "epoch": null,
            "comments": null,
            "reference": "McConnachie12",
            "regime": null
        }
    ],
    "ProperMotions": [
        {
            "pm_ra": -0.4099999964237213,
            "pm_ra_error": null,
            "pm_ra_error_upper": 0.009999999776482582,
            "pm_ra_error_lower": 0.009999999776482582,
            "pm_dec": 0.03999999910593033,
            "pm_dec_error": null,
            "pm_dec_error_upper": 0.009999999776482582,
            "pm_dec_error_lower": 0.009999999776482582,
            "adopted": true,
            "comments": null,
            "reference": "McConnachie12"
        }
    ],
    "RadialVelocities": [
        {
            "rv_kms": 224.1999969482422,
            "rv_error": null,
            "rv_error_upper": 0.10000000149011612,
            "rv_error_lower": 0.10000000149011612,
            "adopted": true,
            "comments": null,
            "reference": "McConnachie12"
        }
    ]
}